{"hit_00":{"sw":36,"sh":21,"sx":98,"sy":81,"tx":6,"ty":9,"ow":48,"oh":32,"px":30,"py":25},"hit_01":{"sw":36,"sh":21,"sx":100,"sy":108,"tx":6,"ty":10,"ow":48,"oh":32,"px":30,"py":26},"hit_02":{"sw":34,"sh":23,"sx":66,"sy":108,"tx":7,"ty":8,"ow":48,"oh":32,"px":31,"py":24},"hit_03":{"sw":32,"sh":26,"sx":100,"sy":0,"tx":8,"ty":5,"ow":48,"oh":32,"px":32,"py":21},"hit_04":{"sw":32,"sh":28,"sx":0,"sy":54,"tx":8,"ty":3,"ow":48,"oh":32,"px":32,"py":19},"idle_00":{"sw":32,"sh":28,"sx":32,"sy":54,"tx":8,"ty":4,"ow":48,"oh":32,"px":32,"py":20},"idle_01":{"sw":32,"sh":28,"sx":32,"sy":54,"tx":8,"ty":4,"ow":48,"oh":32,"px":32,"py":20},"idle_02":{"sw":32,"sh":28,"sx":32,"sy":54,"tx":8,"ty":4,"ow":48,"oh":32,"px":32,"py":20},"idle_03":{"sw":32,"sh":28,"sx":68,"sy":0,"tx":8,"ty":4,"ow":48,"oh":32,"px":32,"py":20},"idle_04":{"sw":32,"sh":27,"sx":0,"sy":82,"tx":8,"ty":5,"ow":48,"oh":32,"px":32,"py":21},"idle_05":{"sw":32,"sh":26,"sx":66,"sy":82,"tx":8,"ty":6,"ow":48,"oh":32,"px":32,"py":22},"idle_06":{"sw":32,"sh":26,"sx":102,"sy":28,"tx":8,"ty":6,"ow":48,"oh":32,"px":32,"py":22},"idle_07":{"sw":34,"sh":26,"sx":68,"sy":28,"tx":7,"ty":6,"ow":48,"oh":32,"px":31,"py":22},"idle_08":{"sw":34,"sh":27,"sx":0,"sy":0,"tx":7,"ty":5,"ow":48,"oh":32,"px":31,"py":21},"run_00":{"sw":30,"sh":27,"sx":0,"sy":109,"tx":2,"ty":2,"ow":36,"oh":30,"px":20,"py":17},"run_01":{"sw":30,"sh":27,"sx":32,"sy":107,"tx":2,"ty":1,"ow":36,"oh":30,"px":20,"py":16},"run_02":{"sw":30,"sh":27,"sx":32,"sy":107,"tx":2,"ty":1,"ow":36,"oh":30,"px":20,"py":16},"run_03":{"sw":30,"sh":27,"sx":98,"sy":54,"tx":2,"ty":2,"ow":36,"oh":30,"px":20,"py":17},"run_04":{"sw":34,"sh":25,"sx":64,"sy":54,"tx":0,"ty":5,"ow":36,"oh":30,"px":18,"py":20},"run_05":{"sw":34,"sh":25,"sx":64,"sy":54,"tx":0,"ty":5,"ow":36,"oh":30,"px":18,"py":20},"run_06":{"sw":34,"sh":27,"sx":0,"sy":27,"tx":0,"ty":2,"ow":36,"oh":30,"px":18,"py":17},"run_07":{"sw":34,"sh":27,"sx":34,"sy":0,"tx":0,"ty":1,"ow":36,"oh":30,"px":18,"py":16},"run_08":{"sw":34,"sh":27,"sx":34,"sy":0,"tx":0,"ty":1,"ow":36,"oh":30,"px":18,"py":16},"run_09":{"sw":34,"sh":27,"sx":34,"sy":27,"tx":0,"ty":2,"ow":36,"oh":30,"px":18,"py":17},"run_10":{"sw":34,"sh":25,"sx":32,"sy":82,"tx":0,"ty":5,"ow":36,"oh":30,"px":18,"py":20},"run_11":{"sw":34,"sh":25,"sx":32,"sy":82,"tx":0,"ty":5,"ow":36,"oh":30,"px":18,"py":20}}